{
  "type": "agritechtwo:tree",
  "drops": [
    {
      "chance": 1.0,
      "item": "minecraft:oak_log",
      "max": 4,
      "min": 1
    },
    {
      "chance": 0.2,
      "item": "minecraft:azalea",
      "max": 1,
      "min": 1
    },
    {
      "chance": 0.2,
      "item": "minecraft:flowering_azalea",
      "max": 1,
      "min": 1
    },
    {
      "chance": 0.5,
      "item": "minecraft:stick",
      "max": 2,
      "min": 1
    }
  ],
  "sapling": {
    "item": "minecraft:flowering_azalea"
  },
  "soils": [
    {
      "tag": "agritechtwo:tree_soils"
    }
  ]
}